admin_tools_stats/__init__.py
admin_tools_stats/admin.py
admin_tools_stats/app_label_renamer.py
admin_tools_stats/apps.py
admin_tools_stats/charts.py
admin_tools_stats/forms.py
admin_tools_stats/models.py
admin_tools_stats/modules.py
admin_tools_stats/urls.py
admin_tools_stats/utils.py
admin_tools_stats/views.py
admin_tools_stats/fixtures/10_dashboardstatscriteria_status.json
admin_tools_stats/fixtures/20_dashboardstatscriteria_call_type.json
admin_tools_stats/fixtures/initial_data.json
admin_tools_stats/management/commands/recalculate_charts.py
admin_tools_stats/migrations/0001_initial.py
admin_tools_stats/migrations/0002_auto_20190920_1058.py
admin_tools_stats/migrations/0003_auto_20191007_0950.py
admin_tools_stats/migrations/0004_dashboardstats_y_tick_format.py
admin_tools_stats/migrations/0005_auto_20200203_1537.py
admin_tools_stats/migrations/0006_auto_20200205_0944.py
admin_tools_stats/migrations/0007_auto_20200205_1054.py
admin_tools_stats/migrations/0008_auto_20200911_1400.py
admin_tools_stats/migrations/0009_auto_20200928_1003.py
admin_tools_stats/migrations/0010_dashboardstats_show_to_users.py
admin_tools_stats/migrations/0011_auto_20210204_1206.py
admin_tools_stats/migrations/0012_auto_20210207_0859.py
admin_tools_stats/migrations/0013_auto_20210221_1247.py
admin_tools_stats/migrations/0014_auto_20211122_1511.py
admin_tools_stats/migrations/0015_auto_20211209_0822.py
admin_tools_stats/migrations/0016_dashboardstats_cache_values.py
admin_tools_stats/migrations/0017_alter_dashboardstats_options_and_more.py
admin_tools_stats/migrations/0018_alter_dashboardstats_options.py
admin_tools_stats/migrations/0019_criteriatostatsm2m_recalculate.py
admin_tools_stats/migrations/0020_alter_dashboardstats_graph_key.py
admin_tools_stats/migrations/0021_auto_20230210_1102.py
admin_tools_stats/migrations/0022_dashboardstats_queryset_modifiers.py
admin_tools_stats/migrations/0023_alter_criteriatostatsm2m_choices_based_on_time_range.py
django_admin_charts-1.5.0.dist-info/METADATA
django_admin_charts-1.5.0.dist-info/WHEEL
django_admin_charts-1.5.0.dist-info/top_level.txt
django_admin_charts-1.5.0.dist-info/RECORD
