Metadata-Version: 2.1
Name: django-admin-charts
Version: 1.5.0
Summary: django-admin-charts - Easily configurable charts statistics for `django-admin` and `django-admin-tools`
Home-page: https://github.com/PetrDlouhy/django-admin-charts
Author: Petr Dlouhy
Author-email: petr.dlouhy@email.cz
License: MIT License
Classifier: Development Status :: 5 - Production/Stable
Classifier: Environment :: Web Environment
Classifier: Framework :: Django
Classifier: Intended Audience :: Developers
Classifier: License :: OSI Approved :: MIT License
Classifier: Operating System :: OS Independent
Classifier: Programming Language :: Python
Classifier: Programming Language :: Python :: 3
Classifier: Programming Language :: Python :: 3.6
Classifier: Programming Language :: Python :: 3.7
Classifier: Programming Language :: Python :: 3.8
Classifier: Programming Language :: Python :: 3.9
Classifier: Programming Language :: Python :: 3.10
Classifier: Topic :: Software Development :: Libraries :: Python Modules
Requires-Dist: django-memoize
Requires-Dist: django-nvd3>=0.5.0
Requires-Dist: django-bower
Requires-Dist: python-dateutil
Requires-Dist: django-multiselectfield
Requires-Dist: datetime_truncate
Requires-Dist: backports.zoneinfo; python_version < "3.9"
Requires-Dist: Django>=2.0; python_version >= "3.0"
